MANIFEST.in
README.md
requirements.txt
setup.cfg
setup.py
chainerrl_visualizer/__init__.py
chainerrl_visualizer/job_worker.py
chainerrl_visualizer/launcher.py
chainerrl_visualizer/web_server.py
chainerrl_visualizer.egg-info/PKG-INFO
chainerrl_visualizer.egg-info/SOURCES.txt
chainerrl_visualizer.egg-info/dependency_links.txt
chainerrl_visualizer.egg-info/requires.txt
chainerrl_visualizer.egg-info/top_level.txt
chainerrl_visualizer/config/__init__.py
chainerrl_visualizer/config/agent.py
chainerrl_visualizer/job_dispatchers/__init__.py
chainerrl_visualizer/job_dispatchers/dispatch_rollout_job.py
chainerrl_visualizer/job_dispatchers/dispatch_saliency_job.py
chainerrl_visualizer/server_tasks/__init__.py
chainerrl_visualizer/server_tasks/prepare_rollout_dir.py
chainerrl_visualizer/server_tasks/rollout_ids.py
chainerrl_visualizer/server_tasks/rollout_log.py
chainerrl_visualizer/static/dist/chainerrl_visualizer.js
chainerrl_visualizer/templates/__init__.py
chainerrl_visualizer/templates/index.html
chainerrl_visualizer/utils/__init__.py
chainerrl_visualizer/utils/jsonize_datetime.py
chainerrl_visualizer/utils/string_generators.py
chainerrl_visualizer/views/__init__.py
chainerrl_visualizer/views/agent_profile.py
chainerrl_visualizer/views/rollout.py
chainerrl_visualizer/views/saliency.py
chainerrl_visualizer/views/server_state.py
chainerrl_visualizer/worker_jobs/__init__.py
chainerrl_visualizer/worker_jobs/rollout_job.py
chainerrl_visualizer/worker_jobs/saliency_job.py
tests/worker_jobs/__init__.py
tests/worker_jobs/test_rollout_job.py