Metadata-Version: 1.0
Name: chainerrl-visualizer
Version: 0.1.0
Summary: Visualizer for ChainerRL
Home-page: UNKNOWN
Author: sykwer
Author-email: sykwer@gmail.com
License: UNKNOWN
Platform: UNKNOWN
